[
  {"version":2},
  {"ingredient":{"id":"simulated:iron_handle"},"type":"item_stack","bookmarkType":"INGREDIENT"},
  {"ingredient":{"id":"createaddition:rolling_mill"},"type":"item_stack","bookmarkType":"INGREDIENT"},
  {"ingredient":{"id":"simulated:spring"},"type":"item_stack","bookmarkType":"INGREDIENT"},
  {"ingredient":{"id":"simulated:rope_connector"},"type":"item_stack","bookmarkType":"INGREDIENT"},
  {"ingredient":{"id":"simulated:rope_coupling"},"type":"item_stack","bookmarkType":"INGREDIENT"},
  {"ingredient":{"id":"createbigcannons:spring_wire"},"type":"item_stack","bookmarkType":"INGREDIENT"},
  {"ingredient":{"id":"create:minecart_coupling"},"type":"item_stack","bookmarkType":"INGREDIENT"},
  {"ingredient":{"id":"immersiveengineering:stick_iron"},"type":"item_stack","bookmarkType":"INGREDIENT"},
  {"ingredient":{"id":"irons_spellbooks:arcane_anvil"},"type":"item_stack","bookmarkType":"INGREDIENT"},
  {"ingredient":{"id":"occultengineering:mechanical_pulverizer","components":{"occultengineering:crushing_item_tier":4}},"type":"item_stack","bookmarkType":"INGREDIENT"}
]